tsbatteries/__init__.py
tsbatteries/models/__init__.py
tsbatteries/models/ncde.py
tsbatteries/models/retain.py
tsbatteries/models/rnn.py
tsbatteries/models/utils.py
tsbatteries/preprocessing/__init__.py
tsbatteries/preprocessing/_mixin.py
tsbatteries/preprocessing/impute.py
tsbatteries/preprocessing/misc.py
tsbatteries/preprocessing/pipeline.py
tsbatteries/preprocessing/problem.py
tsbatteries/preprocessing/scale.py
tsbatteries/preprocessing/split.py
tsbatteries/tests/__init__.py
tsbatteries/tests/helpers.py
tsbatteries/tests/test_models.py
tsbatteries/tests/test_ncde.py
tsbatteries/tests/preprocessing/__init__.py
tsbatteries/tests/preprocessing/test_impute.py
tsbatteries/tests/preprocessing/test_misc.py
tsbatteries/tests/preprocessing/test_pipeline.py
tsbatteries-0.1.4.dist-info/AUTHORS
tsbatteries-0.1.4.dist-info/METADATA
tsbatteries-0.1.4.dist-info/WHEEL
tsbatteries-0.1.4.dist-info/dependency_links.txt
tsbatteries-0.1.4.dist-info/pbr.json
tsbatteries-0.1.4.dist-info/top_level.txt
tsbatteries-0.1.4.dist-info/RECORD
